{
    "daily": {
        "location": "/join neyear",
        "item": "4 New 0 AC Rare Weapons",
        "date": "January 02, 2022",
        "image": "https://i.imgur.com/o0RW70Y.jpg",
        "link": "https://twitter.com/twitter/statuses/1477500985715134465",
        "quest": "",
        "enemy": [
            "2022 Ball",
            "http://aqwwiki.wikidot.com/2022-Ball"
        ]
    },
    "boost": {
        "item": "72 Hour Double Class Points, Rep, Gold, And Exp Boosts",
        "startsin": "December 31, 2021",
        "endsin": "03 January 2022"
    }
}