{
    "daily": {
        "location": "/join helsgrove",
        "item": "0 AC Frostval Barbarian Blade",
        "date": "December 11, 2021",
        "image": "https://i.imgur.com/yCnlkVX.jpg",
        "link": "https://twitter.com/twitter/statuses/1469534911606386689",
        "quest": "",
        "enemy": [
            "Helsdottir",
            "http://aqwwiki.wikidot.com/Helsdottir"
        ]
    },
    "boost": {
        "item": "48 Hour Double Rep (Reputation) Boost",
        "startsin": "December 10, 2021",
        "endsin": "12 December 2021"
    }
}