{
    "daily": {
        "location": "/join tercessuinotlim",
        "item": "0 AC Archfiend Mage'S Wand",
        "date": "January 12, 2022",
        "image": "https://i.imgur.com/Aqw9UCV.jpg",
        "link": "https://twitter.com/twitter/statuses/1481113707493007361",
        "quest": "",
        "enemy": [
            "Evil Elemental",
            "http://aqwwiki.wikidot.com/Evil-Elemental"
        ]
    },
    "boost": {
        "item": "Double Drop Rate And Double Quantity Boost On Unidentified 34 And 35",
        "startsin": "January 06, 2022",
        "endsin": "09 January 2022"
    }
}