{
    "Imperial Chunin": {
        "acronym": "ImC"
    },
    "Dragon of Time": {
        "acronym": "DoT",
        "location": "Complete multiple Questline, /classhall"
    },
    "Dark Master of Moglins": {
        "acronym": "DMoM"
    },
    "StoneCrusher": {
        "acronym": "IT"
    },
    "The Collector": {
        "acronym": "Collector",
        "location": "/collection, merge daily tokens"
    },
    "ArchPaladin": {
        "bludrut": 6
    },
    "Blaze Binder": {
        "stats": [
            "null",
            "null",
            "null",
            "null",
            "null",
            "null",
            2
        ]
    },
    "MindBreaker": {
        "stats": [
            4,
            "null",
            "null",
            "null",
            "null",
            "null",
            "null"
        ],
        "bludrut": 2
    },
    "Sentinel": {
        "stats": [
            "null",
            "null",
            2,
            "null",
            5,
            "null",
            "null"
        ],
        "bludrut": 6
    },
    "Legion Revenant": {
        "stats": [
            "null",
            "null",
            6,
            "null",
            "null",
            "null",
            "null"
        ],
        "bludrut": 6,
        "location": "Insane Quest, /revenant, needs one dark caster class"
    },
    "Elemental Dracomancer": {
        "stats": [
            3,
            4,
            2,
            "null",
            "null",
            "null",
            "null"
        ],
        "bludrut": 6
    },
    "Horc Evader": {
        "stats": [
            "null",
            5,
            "null",
            "null",
            3,
            "null",
            "null"
        ],
        "bludrut": 3
    },
    "Great Thief": {
        "stats": [
            6,
            "null",
            "null",
            "null",
            6,
            "null",
            "null"
        ],
        "bludrut": 6
    },
    "Void Highlord": {
        "stats": [
            6,
            "null",
            "null",
            6,
            "null",
            "null",
            "null"
        ],
        "location": "merge, /tercessuinotlim"
    },
    "ShadowStalker of Time": {
        "stats": [
            "null",
            "null",
            "null",
            6,
            "null",
            "null",
            "null"
        ],
        "type": "available",
        "location": "/curio, 6k AC, Speak to Chronix"
    },
    "Immortal Chronomancer": {
        "stats": [
            "null",
            "null",
            "null",
            6,
            "null",
            "null",
            "null"
        ],
        "type": "available",
        "location": "/curio, 6k AC, Speak to Chronis"
    },
    "Corrupted Chronomancer": {
        "stats": [
            "null",
            "null",
            "null",
            6,
            "null",
            "null",
            "null"
        ]
    },
    "ChronoCorruptor": {
        "acronym": "CcoR"
    },
    "Underworld Chronomancer": {
        "acronym": "UC",
        "stats": [
            "null",
            "null",
            "null",
            6,
            "null",
            "null",
            "null"
        ]
    },
    "Chrono DragonKnight": {
        "stats": [
            "null",
            "null",
            "null",
            6,
            "null",
            "null",
            "null"
        ]
    },
    "ChronoCommander": {
        "acronym": "ChronoCom, ChComm",
        "stats": [
            "null",
            "null",
            "null",
            6,
            "null",
            "null",
            "null"
        ]
    },
    "Chronomancer": {
        "stats": [
            "null",
            "null",
            "null",
            5,
            "null",
            "null",
            "null"
        ]
    },
    "Lycan": {
        "stats": [
            "null",
            "null",
            "null",
            "null",
            "null",
            1,
            "null"
        ],
        "bludrut": 5
    },
    "Royal BattleMage": {
        "stats": [
            "null",
            "null",
            "null",
            "null",
            4,
            "null",
            "null"
        ],
        "bludrut": 4
    },
    "Vampire Lord": {
        "acronym": "RVL",
        "stats": [
            2,
            2,
            2,
            0,
            2,
            5,
            4
        ],
        "bludrut": 5
    },
    "LightCaster": {
        "stats": [
            "null",
            "null",
            6,
            "null",
            "null",
            "null",
            "null"
        ],
        "bludrut": 5,
        "location": "/celestialrealm, finish quest, needs 1k AC Light Mage"
    },
    "ShadowScythe General": {
        "acronym": "SG"
    },
    "Infinite Legion Dark Caster": {
        "type": "available"
    }
}